BUILD.rst
CHANGES.rst
COPYRIGHT.txt
INSTALL.rst
LICENSE.txt
MANIFEST.in
README.rst
README.txt
requirements.txt
robot.bmp
setup.cfg
setup.py
doc/LDTPLibrary.html
doc/generate.py
src/ez_setup.py
src/LDTPLibrary/__init__.py
src/LDTPLibrary/version.py
src/LDTPLibrary/keywords/__init__.py
src/LDTPLibrary/keywords/_exception.py
src/LDTPLibrary/keywords/_screenshot.py
src/LDTPLibrary/keywords/_table.py
src/LDTPLibrary/keywords/keywordgroup.py
src/LDTPLibrary/keywords/ldtpkw.py
src/LDTPLibrary/keywords/logging.py
src/LDTPLibrary/keywords/runonfailure.py
src/LDTPLibrary/utils/__init__.py
src/LDTPLibrary/utils/librarylistener.py
src/LDTPLibrary/utils/events/__init__.py
src/LDTPLibrary/utils/events/event.py
src/LDTPLibrary/utils/events/scope_event.py
src/robotframework_ldtplibrary.egg-info/PKG-INFO
src/robotframework_ldtplibrary.egg-info/SOURCES.txt
src/robotframework_ldtplibrary.egg-info/dependency_links.txt
src/robotframework_ldtplibrary.egg-info/requires.txt
src/robotframework_ldtplibrary.egg-info/top_level.txt