Metadata-Version: 1.1
Name: robotframework-ldtplibrary
Version: 10.2.2
Summary: linux desktop testing library for Robot Framework
Home-page: https://github.com/wywincl/LDTPLibrary
Author: John.Wang
Author-email: 254263208@qq.com
License: Apache License 2.0
Keywords: robotframework testing test automation ldtp dogtail AT-SPI GUI
Platform: any
Classifier: Development Status :: 5 - Production/Stable
Classifier: License :: OSI Approved :: Apache Software License
Classifier: Operating System :: OS Independent
Classifier: Programming Language :: Python
Classifier: Topic :: Software Development :: Testing
